{
  "url": "https://steps-admin.herokuapp.com/api",
  "baseUrl": "https://stepsroobot.herokuapp.com/",
  "videoUrl": "https://youtu.be/WpHtdkKQz8Q",
  "done": {
    "path": "static/images/done/",
    "images": [
      "03_A_Swish_v01.gif",
      "03_B_Party_v01.gif",
      "03_C_Firework_v02.gif",
      "03_D_PomPom_v01.gif",
      "space_v2.gif"
    ]
  },
  "help": {
    "path": "static/images/help/",
    "images": [
      "Coach_Says.gif"
    ]
  },
  "checkin": {
    "path": "static/images/checkin/",
    "images": [
      "02_A_Light_v03.gif",
      "02_B_Fence_v01.gif",
      "02_C_Sunglasses_v01.gif",
      "02_D_Blinds_v01.gif",
      "02_E_Binoculars_v02.gif"
    ]
  },
  "stories": {
    "path": "static/images/stories/",
    "images": [
      "Stories.gif"
    ]
  },
  "tasks": {
    "path": "static/images/tasks/",
    "images": [
      "04_Number1.gif",
      "04_Number2.gif",
      "04_Number3.gif",
      "04_Number4.gif",
      "04_Number5.gif",
      "04_Number6.gif",
      "04_Number7.gif",
      "04_Number8.gif",
      "04_Number9.gif"
    ]
  },
  "welcome": {
    "path": "static/images/welcome/",
    "images": [
      "01_A_Hello_v01.gif"
    ],
    "workplanImgUrl": "01_B_Map_v01.gif",
    "introCelebrateUrl": "01_C_FirstCelebrate_v01.gif"
  }
}
